Workbook

Sheet Nacionalizado
A1: Somos G2E. Una empresa de energias renovables con mas de 15 años de experiencia en el sector. CONTACTANOS POR WHATSAPP AL: 11-3652-0821 Direccion comercial y administrativa: Vedia 3892, CABA, Argentina. NO VENDEMOS A USUARIO FINAL. NO VENDEMOS REPUESTOS NI DAMOS SERVICE A EQUIPOS DE TERCEROS . ESTE LISTADO DE PRECIOS ES PARA INSTALADORES / INTEGRADORES | E1: www.g2e.com.ar
A2: LEGAJO IMPOSITIVO
A3: CONDICIONES COMERCIALES: 1)Tipo de cambio: BNA billete vendedor del momento del pago 2)Forma de pago: Transferencia o depositos por ventanilla. Echeq al dia en casos previamente acordados. Tomamos pagos en USD (deposito en BNA o transferencia, ambos sin recargo) Echeq a 30 y 60 dias para clientes con historial de compra con tasa de recargo aproximada del 3,5% (a 30) a definir segun operacion. 3)Entrega: 3 a 5 dias habiles desde acreditado el pago para despachar en transporte en CABA. Se puede retirar por deposito dependiendo el producto. 4)IVA: Precios expresados sin IVA. 5)Stock: Confirmar stock previamente por whatsap. 6) Garantia: todos los productos cuentan con garantia. La garantia se hace efectiva con el equipo enviado a nuestros laboratorios en CABA. 7) Minimo de compra: USD 1000 + IVA
A4: Ultimas actualizaciones | C4: 06/5: ingresan hibridos DEYE y algunos con disminucion de precios. Ingresan baterias DEYE F12 y F16
C5: 11/5: reduccion precio huawei 150kw
C6: 12/5: ingresa jinko bifacial 620w buen precio
C7: 13/5: Opcion de impo contenedor entero de paneles a pedido. Consultar
C8: 22/5: ingresa estructura coplanar sunsolar
C9: 27/5: ingresn paneles jino y ja solar en buen precio minimo 3 pallet
C10: 01/06: aviso de aumento de paneles desde china
C11: 01/06: NOVEDAD INGRESAN INVERSORES ON GRID SUNGROW
C12: 03/06: poco stock baterias pro b de deye
C13: 08/06: ingresa bateria HOPE 16.0 (16KWH) compatible con inversores SPF
C14: 10/6: PANELES ASTROENERGY PRECIAZO X PALLET CERRADO EN LIQUIDACION
A23: Codigo | B23: DISPONIBILIDAD TENTATIVA. STOCK Y PRECIO A CONFIRMAR POR WHATSAPP | C23: PRODUCTO
A24: PANELES
A25: ='.'!A2 -> 1 | B25: ='.'!C2 -> INMEDIATO | C25: ='.'!D2 -> LONGI - 430w HiMOX6-LR5-54HTB (USD/watt) | D25: ='.'!F2 -> 0.23023256
A26: ='.'!A3 -> 2 | B26: ='.'!C3 -> INMEDIATO | C26: ='.'!D3 -> LONGI - 645w LR7-72HVH N-Type HPBC 2.0, HI-MO X10 (USD/watt) . se vende por unidad 15% mas caro. | D26: ='.'!F3 -> 0.1914 | E26: link de descarga
A27: ='.'!A4 -> 3 | B27: ='.'!C4 -> INMEDIATO | C27: ='.'!D4 -> LONGI - 610w BIFACIAL (USD/watt) - se vende por unidad 15% mas caro. | D27: 0.21 | E27: link de descarga
A28: ='.'!A5 -> 4 | B28: ='.'!C5 -> SIN FECHA ESTIMADA | C28: ='.'!D5 -> TRINA - BIFACIAL 570 (USD/watt).- se vende pallet cerrado | D28: ='.'!F5 -> 0.161 | E28: link de descarga
A29: ='.'!A6 -> 5 | B29: ='.'!C6 -> SIN FECHA ESTIMADA | C29: ='.'!D6 -> TRINA - BIFACIAL 605w TIPO N (USD/watt)- se vende pallet cerrado | D29: ='.'!F6 -> 0.161 | E29: link de descarga
A30: ='.'!A7 -> 6 | B30: ='.'!C7 -> INMEDIATO | C30: ='.'!D7 -> TRINA - BIFACIAL 615w TIPO N (USD/watt)- se vende pallet cerrado | D30: ='.'!F7 -> 0.1749
A31: ='.'!A8 -> 7 | B31: ='.'!C8 -> INMEDIATO | C31: ='.'!D8 -> TRINA - MONOFACIAL 620w TIPO N (USD/watt)- se vende pallet cerrado | D31: ='.'!F8 -> 0.1749
A32: ='.'!A9 -> 8 | B32: ='.'!C9 -> LIQUIDACION. Quedan 9 unidades | C32: ='.'!D9 -> TRINA - BIFACIAL 630w TIPO N (USD/watt)- se vende pallet cerrrado (o por unidad con costo de flete al transporte de usd 35+iva por entrega total) | D32: ='.'!F9 -> 0.165 | E32: link de descarga
A33: ='.'!A10 -> 9 | B33: ='.'!C10 -> INMEDIATO | C33: ='.'!D10 -> TRINA - MONOFACIAL 670w (USD/watt).- se vende pallet cerrado. Se entrega en transporte en Cordoba | D33: ='.'!F10 -> 0.1815 | E33: link de descarga
A34: ='.'!A11 -> 10 | B34: ='.'!C11 -> INMEDIATO | C34: ='.'!D11 -> TRINA - BIFACIAL 715 (USD/watt).- se vende pallet cerrado. Se retira por depo Soldati o va a transporte en CTC | D34: ='.'!F11 -> 0.1947 | E34: link de descarga
A35: ='.'!A12 -> 11 | B35: ='.'!C12 -> INMEDIATO | C35: ='.'!D12 -> JINKO - M/M 475w TIGER NEO JKM475-60HL4. se vende pallet cerrado o por unidad 30% mas caro | D35: 0.166 | E35: link de descarga
A36: ='.'!A13 -> 12 | B36: ='.'!C13 -> LIQUIDACION. Quedan 5 unidades | C36: ='.'!D13 -> JINKO - BIFACIAL 585 w 72HL4-BDV (USD/watt)- Se retiran por depo soldati | D36: ='.'!E13 -> 0.15 | E36: link de descarga
A37: ='.'!A14 -> 46034 | B37: ='.'!C14 -> INMEDIATO | C37: ='.'!D14 -> JINKO - MONOF 585 w 72HL4-BDV (USD/watt)- Se envia a transporte en Cordoba | D37: ='.'!F14 -> 0.18955
A38: ='.'!A15 -> 13 | B38: ='.'!C15 -> IMPO: 90 a 120 dias corridos | C38: ='.'!D15 -> JINKO - BIF 725 w TIPO N (USD/watt) se vende contenedor entero (20 pallet de 33 u) | D38: 0.15 | E38: link de descarga
A39: ='.'!A16 -> 14 | B39: ='.'!C16 -> INMEDIATO | C39: ='.'!D16 -> JINKO - BIFACIAL TIPO N, 620w(USD/watt)-se vende por unidad 32% mas caro. | D39: ='.'!F16 -> 0.17446 | E39: link de descarga
A40: ='.'!A17 -> 15 | B40: ='.'!C17 -> INMEDIATO | C40: ='.'!D17 -> JINKO - M/M TOPcon, 715w(USD/watt)-se vende palet cerrado | D40: ='.'!F17 -> 0.155 | E40: link de descarga
A41: ='.'!A18 -> 16 | B41: ='.'!C18 -> INMEDIATO | C41: ='.'!D18 -> JA SOLAR - BIFACIAL 600w - se vende pallet cerrado | D41: ='.'!F18 -> 0.155 | E41: link de descarga
A42: ='.'!A19 -> 17 | B42: ='.'!C19 -> INMEDIATO | C42: ='.'!D19 -> TRINA - BiFACIAL 620w TIPO N (USD/watt)-se vende pallet cerrado - | D42: ='.'!F19 -> 0.1749 | E42: link de descarga
A43: ='.'!A20 -> 18 | B43: ='.'!C20 -> INMEDIATO. 5 a 10 dias habiles para despachar | C43: ='.'!D20 -> LUXEN 144C. Mono Serie 4 410Wp PERC- se vende por unidad 2.5% mas caro (35mm) -5 a 10 dias habiles para despachar | D43: ='.'!F20 -> 0.16576
A44: ='.'!A21 -> 19 | B44: ='.'!C21 -> SIN FECHA ESTIMADA | C44: ='.'!D21 -> LUXEN 144C. Mono Serie 5 550Wp PERC (35mm)- se vende por unidad 2.5% mas caro - 5 a 10 dias habiles para despachar | D44: ='.'!F21 -> 0.16128
A45: ='.'!A22 -> 20 | B45: ='.'!C22 -> SIN FECHA ESTIMADA | C45: ='.'!D22 -> LUXEN - 144C. M/M . Serie 5 550Wp PERC BLACK (35mm)- se vende por unidad 2.5% mas caro - 5 a 10 dias habiles para despachar | D45: ='.'!F22 -> 0.165 | E45: link de descarga
A46: ='.'!A23 -> 21 | B46: ='.'!C23 -> INMEDIATO. Se vende por unidad | C46: ='.'!D23 -> LUXEN - 132C. M/M N5 585Wp TOPcon- se vende por unidad 2.5% mas caro - 5 a 10 dias habiles para despachar | D46: ='.'!F23 -> 0.1694 | E46: link de descarga
A47: ='.'!A24 -> 22 | B47: ='.'!C24 -> INMEDIATO. Se vende por unidad | C47: ='.'!D24 -> LUXEN - 132C. N5 RECT 585Wp TOPCon GoG bifacial - se vende por unidad 2.5% mas caro (36u x pallet) - 5 a 10 dias habiles para despachar | D47: ='.'!F24 -> 0.1694 | E47: link de descarga
A48: ='.'!A25 -> 23 | B48: ='.'!C25 -> INMEDIATO. Se vende por unidad | C48: ='.'!D25 -> LUXEN 144C. Mono N5 RECT 630Wp TOPCon- se vende por unidad 2.5% mas caro. - 5 a 10 dias habiles para despachar | D48: ='.'!F25 -> 0.1694 | E48: link de descarga
A49: ='.'!A26 -> 24 | B49: ='.'!C26 -> INMEDIATO. Se vende por unidad | C49: ='.'!D26 -> LUXEN - 132C. Mono N6 700Wp TOPCon GoG Bifacial- se vende por unidad 2.5% mas caro (34u x pallet) - 5 a 10 dias habiles para despachar | D49: ='.'!F26 -> 0.1694 | E49: link de descarga
A50: ='.'!A27 -> 25 | B50: ='.'!C27 -> LIQUIDACION PALLET CERRADO | C50: ='.'!D27 -> ASTROENERGY - BIFACIAL 144 CEL. N TYPE 575W CABLE 1.4M. Se vende pallet cerrado. Se entrega en transporte en Cordoba | D50: ='.'!E27 -> 0.15 | E50: link de descarga
A51: ='.'!A28 -> 26 | B51: ='.'!C28 -> LIQUIDACION. Quedan 2 unidades | C51: ='.'!D28 -> ASTROENERGY - BIFACIAL 144 CEL. N TYPE 585W - se vende por unidad. Se entrega en depo soldati u oficina DOT | D51: ='.'!E28 -> 0.14
A52: ='.'!A29 -> 27 | B52: ='.'!C29 -> INMEDIATO | C52: ='.'!D29 -> ASTROENERGY - 615w -N7_CHSM66RN(DG)F-BH dual glass - BIFACIAL. Se retira por depo Soldati | D52: ='.'!F29 -> 0.22357724 | E52: link de descarga
A53: ='.'!A30 -> 28 | B53: ='.'!C30 -> SIN FECHA ESTIMADA | C53: ='.'!D30 -> AMERISOLAR- Policristalino 340w. Pallet 36 unidades. se vende pallet cerrado | D53: ='.'!F30 -> 0.28336
A54: ='.'!A31 -> 29 | B54: ='.'!C31 -> SIN FECHA ESTIMADA | C54: ='.'!D31 -> AMERISOLAR - MONOCRISTALINO AS-7M108N-HC-440W. se vende por unidad 32% mas caro. 36u x pallet -Entrega gratis en GBA. | D54: ='.'!F31 -> 0.187 | E54: link de descarga
A55: ='.'!A32 -> 30 | B55: ='.'!C32 -> SIN FECHA ESTIMADA | C55: ='.'!D32 -> AMERISOLAR - MONOCRISTALINO AS-7M144-HC-555W. se vende por unidad 32% mas caro. -Entrega gratis en GBA. | D55: ='.'!F32 -> 0.1668106 | E55: link de descarga
A56: ='.'!A33 -> 31 | B56: ='.'!C33 -> INMEDIATO. Se vende por unidad | C56: ='.'!D33 -> AMERISOLAR - MONOCRISTALINO AS-7M144-HC-580W. precio pallet cerrado. Entrega gratis en GBA. Por unidad 30% mas caro | D56: ='.'!F33 -> 0.15859218 | E56: link de descarga
A57: ='.'!A34 -> 32 | B57: ='.'!C34 -> SIN FECHA ESTIMADA | C57: ='.'!D34 -> AMERISOLAR - MONOCRISTALINO AS-8M120-HC-600W. se vende por unidad 30% mas caro. | D57: ='.'!F34 -> 0.14
A58: ='.'!A35 -> 33 | B58: ='.'!C35 -> INMEDIATO. Quedan 28 unidades se venden juntas | C58: ='.'!D35 -> SUNPRO - Monoc, TOPCON, SPDG585-N144M10-585W con Marco Negro. BIFACIAL. se venden las 28 unidades juntas | D58: ='.'!F35 -> 0.1595 | E58: link de descarga
A59: ='.'!A36 -> 34 | B59: ='.'!C36 -> INMEDIATO | C59: ='.'!D36 -> HAITAI - Monocristalino, media celda, Anti LID HTM585DMH5-72NT-585W. Pallet 36 unidades. se vende por unidad 32% mas caro. | D59: ='.'!F36 -> 0.17504197 | E59: link de descarga
A60: ='.'!A37 -> 35 | B60: ='.'!C37 -> INGRESA ABRIL | C60: ='.'!D37 -> HAITAI - Monocristalino, media celda, HTM415MH5-54 415W. Pallet 36 unidades. se vende por unidad 32% mas caro. | D60: ='.'!F37 -> 0.1495 | E60: link de descarga
A61: ='.'!A38 -> 36 | B61: ='.'!C38 -> INMEDIATO | C61: ='.'!D38 -> HAITAI, Monocristalino, media celda, Anti LID, Bifacial, HTM630DMH6-66NT BIFACIAL 630W. Pallet 36 unidades.se vende por unidad 32% mas caro | D61: ='.'!F38 -> 0.1826 | E61: link de descarga
A62: ='.'!A39 -> 37 | B62: ='.'!C39 -> INMEDIATO | C62: ='.'!D39 -> TLC - Anti LID TCL-MI585 DH182-72NT 585W BIFACIAL. Pallet 36 unidades. se vende por unidad 32% mas caro | D62: ='.'!F39 -> 0.16264487 | E62: link de descarga
A63: ='.'!A40 -> 38 | B63: ='.'!C40 -> INMEDIATO | C63: ='.'!D40 -> NUUKO - monof 550w (pallet 31 u) - se vende minimo 10 u | D63: 0.161 | E63: link de descarga
A64: ='.'!A41 -> 39 | B64: ='.'!C41 -> INMEDIATO | C64: ='.'!D41 -> NUUKO - bif 615w topcon (pallet 36 u) - se vende minimo 10 u | D64: 0.169 | E64: link de descarga
A65: INVERSORES ON GRID SUNGROW
A66: ='.'!A43 -> 39-1 | B66: ='.'!C43 -> INMEDIATO | C66: ='.'!D43 -> Inversor On-Grid SunGrow Trifasico 15 KW | D66: ='.'!F43 -> 1297.8336
A67: ='.'!A44 -> 39-2 | B67: ='.'!C44 -> INMEDIATO | C67: ='.'!D44 -> Inversor On-Grid SunGrow Trifasico 20 KW | D67: ='.'!F44 -> 1433.993
A68: ='.'!A45 -> 39-3 | B68: ='.'!C45 -> INMEDIATO | C68: ='.'!D45 -> Inversor On-Grid SunGrow Trifasico 25 KW | D68: ='.'!F45 -> 1779.206
A69: ='.'!A46 -> 39-4 | B69: ='.'!C46 -> INMEDIATO | C69: ='.'!D46 -> Inversor On-Grid SunGrow Trifasico 30 KW | D69: ='.'!F46 -> 2044.768
A70: ='.'!A47 -> 39-5 | B70: ='.'!C47 -> INMEDIATO | C70: ='.'!D47 -> Inversor On-Grid SunGrow Trifasico 40 KW | D70: ='.'!F47 -> 2400.607
A71: ='.'!A48 -> 39-6 | B71: ='.'!C48 -> INMEDIATO | C71: ='.'!D48 -> Inversor On-Grid SunGrow Trifasico 50 KW | D71: ='.'!F48 -> 2798.4544
A72: ='.'!A49 -> 39-7 | B72: ='.'!C49 -> INMEDIATO | C72: ='.'!D49 -> Inversor On-Grid SunGrow Trifasico 75 KW | D72: ='.'!F49 -> 3823.975
A73: ='.'!A50 -> 39-8 | B73: ='.'!C50 -> INMEDIATO | C73: ='.'!D50 -> Inversor On-Grid SunGrow Trifasico 110 KW | D73: ='.'!F50 -> 5066.765
A74: ='.'!A51 -> 39-9 | B74: ='.'!C51 -> INMEDIATO | C74: ='.'!D51 -> Inversor On-Grid SunGrow Trifasico 250 KW | D74: ='.'!F51 -> 9942.328
A75: ='.'!A52 -> 39-10 | B75: ='.'!C52 -> INMEDIATO | C75: ='.'!D52 -> Inversor On-Grid SunGrow Trifasico 333 KW | D75: ='.'!F52 -> 12236.719
A76: INVERSORES ON GRID GOODWE
A77: ='.'!A54 -> 40 | B77: ='.'!C54 -> SIN FECHA ESTIMADA | C77: ='.'!D54 -> Inversor de inyección a red GOODWE 1500W Monof. (GW1500 - XS-30) | D77: ='.'!F54 -> 186.3 | E77: link de descarga
A78: ='.'!A55 -> 41 | B78: ='.'!C55 -> INMEDIATO | C78: ='.'!D55 -> IMicronversor de inyección a red GOODWE 2000w Monof. (GW2000-MIS) | D78: ='.'!F55 -> 279.0625 | E78: link de descarga
A79: ='.'!A56 -> 42 | B79: ='.'!C56 -> INMEDIATO | C79: ='.'!D56 -> Inversor de inyección a red GOODWE 3600W Monof. c/AFCI (GW3.6K-DNS-G40) | D79: ='.'!F56 -> 401.375 | E79: link de descarga
A80: ='.'!A57 -> 43 | B80: ='.'!C57 -> INMEDIATO. 5 a 10 dias habiles para despachar | C80: ='.'!D57 -> Inversor de inyección a red GOODWE 6000W Trif. c/AFCI | D80: ='.'!F57 -> 610.88 | E80: link de descarga
A81: ='.'!A58 -> 44 | B81: ='.'!C58 -> INMEDIATO. 5 a 10 dias habiles para despachar | C81: ='.'!D58 -> Inversor de inyección a red GOODWE 10kW Trif. (10K-SDT30) | D81: ='.'!F58 -> 779.52 | E81: link de descarga
A82: ='.'!A59 -> 45 | B82: ='.'!C59 -> SIN FECHA ESTIMADA | C82: ='.'!D59 -> Inversor de inyección a red GOODWE 12kW Trif. c/Wifi | D82: ='.'!F59 -> 2168.2742 | E82: link de descarga
A83: ='.'!A60 -> 46 | B83: ='.'!C60 -> INMEDIATO. 5 a 10 dias habiles para despachar | C83: ='.'!D60 -> Inversor de inyección a red GOODWE 15kW Trif. (15K-SDT-30) | D83: ='.'!F60 -> 860.16 | E83: link de descarga
A84: ='.'!A61 -> 47 | B84: ='.'!C61 -> INMEDIATO. 5 a 10 dias habiles para despachar | C84: ='.'!D61 -> Inversor de inyección a red GOODWE 20kW Trif.(20K-SDT-30) | D84: ='.'!F61 -> 987.84 | E84: link de descarga
A85: ='.'!A62 -> 48 | B85: ='.'!C62 -> INMEDIATO. 5 a 10 dias habiles para despachar | C85: ='.'!D62 -> Inversor de inyección a red GOODWE 25kW Trif. c/AFCI (25K-SDT-C30-AFCI) | D85: ='.'!F62 -> 1113.28 | E85: link de descarga
A86: ='.'!A63 -> 49 | B86: ='.'!C63 -> INMEDIATO. 5 a 10 dias habiles para despachar | C86: ='.'!D63 -> Inversor de inyección a red GOODWE 30kW Trif. c/AFCI (30K-SDT-C30-AFCI) | D86: ='.'!F63 -> 1227.52 | E86: link de descarga
A87: ='.'!A64 -> 50 | B87: ='.'!C64 -> INMEDIATO. 5 a 10 dias habiles para despachar | C87: ='.'!D64 -> Inversor de inyección a red GOODWE 33kW Trif. c/AFCI (30K-SDT-C30-AFCI) | D87: ='.'!F64 -> 1232 | E87: link de descarga
A88: ='.'!A65 -> 51 | B88: ='.'!C65 -> INMEDIATO. 5 a 10 dias habiles para despachar | C88: ='.'!D65 -> Inversor de inyección a red GOODWE 36kW Trif. c/AFCI (30K-SDT-C30-AFCI) | D88: ='.'!F65 -> 1276 | E88: link de descarga
... A95: ='.'!A72 -> 58 | B95: ='.'!C72 -> INMEDIATO. 5 a 10 dias habiles para despachar | C95: ='.'!D72 -> Inversor de inyección a red GOODWE 110kW Trif. C/AFCI | D95: ='.'!F72 -> 3907.2 | E95: link de descarga
A96: ='.'!A73 -> 59 | B96: ='.'!C73 -> INMEDIATO. 5 a 10 dias habiles para despachar | C96: ='.'!D73 -> Inversor de inyección a red GOODWE 100KW Trifasico AFCI | D96: ='.'!F73 -> 4040.96
A97: ='.'!A74 -> 60 | B97: ='.'!C74 -> INMEDIATO. 5 a 10 dias habiles para despachar | C97: ='.'!D74 -> Inversor de inyección a red GOODWE 50kW GW50K-SDT-C30 | D97: 2365
A98: ='.'!A75 -> 61 | B98: ='.'!C75 -> INMEDIATO. 5 a 10 dias habiles para despachar | C98: ='.'!D75 -> Inversor de inyección a red GOODWE 125KW Trifasico. (GW100K GT). Se entrega en transporte en Rosario | D98: ='.'!F75 -> 4374.72
A99: ='.'!A76 -> 62 | B99: ='.'!C76 -> INMEDIATO. 5 a 10 dias habiles para despachar | C99: ='.'!D76 -> Smart meter GMK110 monofasico | D99: ='.'!F76 -> 195.125
A100: ='.'!A77 -> 63 | B100: ='.'!C77 -> INMEDIATO. 5 a 10 dias habiles para despachar | C100: ='.'!D77 -> Smart meter GMK330 trifasico | D100: ='.'!F77 -> 379.5
A101: INVERSORES ON GRID HUAWEI
A102: ='.'!A79 -> 64 | B102: ='.'!C79 -> INMEDIATO | C102: ='.'!D79 -> INVERSOR TRIFASICO HUAWEI SUN2000-40KTL-M3 | D102: ='.'!F79 -> 2711.83
A103: ='.'!A80 -> 65 | B103: ='.'!C80 -> INMEDIATO | C103: ='.'!D80 -> INVERSOR TRIFASICO HUAWEI SUN2000-50KTL-M3 | D103: ='.'!F80 -> 2937.979
A104: ='.'!A81 -> 66 | B104: ='.'!C81 -> INMEDIATO | C104: ='.'!D81 -> INVERSOR TRIFASICO HUAWEI SUN2000-100KTL M2- | D104: ='.'!F81 -> 5645.893 | E104: link de descarga
A105: ='.'!A82 -> 67 | B105: ='.'!C82 -> INMEDIATO | C105: ='.'!D82 -> INVERSOR TRIFASICO HUAWEI SUN2000-150K-MG0 - | D105: ='.'!F82 -> 6325 | E105: link de descarga
A106: ='.'!A83 -> 68 | B106: ='.'!C83 -> INMEDIATO | C106: ='.'!D83 -> INVERSOR TRIFASICO 6MPPT 800V 330KW HUAWEI | D106: ='.'!F83 -> 9898.9
A107: ='.'!A84 -> 69 | B107: ='.'!C84 -> INMEDIATO | C107: ='.'!D84 -> Huawei SmartPS-250A-T0 - Smart Power Sensor | D107: ='.'!F84 -> 173.7
A108: ='.'!A85 -> 70 | B108: ='.'!C85 -> INMEDIATO | C108: ='.'!D85 -> Huawei SDongleA-05 | D108: ='.'!F85 -> 62.1
A109: ='.'!A86 -> 71 | B109: ='.'!C86 -> INMEDIATO | C109: ='.'!D86 -> DongleB-06-AU - Dongle 4G | D109: ='.'!F86 -> 152.1
A110: INVERSORES VOLTRONIC
A111: ='.'!A88 -> 72 | B111: ='.'!C88 -> SIN FECHA ESTIMADA | C111: ='.'!D88 -> INVERSOR OFF GRID - AXPERT VM 2KW | D111: ='.'!F88 -> 520.24
A112: ='.'!A89 -> 73 | B112: ='.'!C89 -> SIN FECHA ESTIMADA | C112: ='.'!D89 -> VOLTRONIC AXPERT VM 1kW | D112: ='.'!F89 -> 322
A113: ='.'!A90 -> 74 | B113: ='.'!C90 -> SIN FECHA ESTIMADA | C113: ='.'!D90 -> VOLTRONIC AXPERT VP 3kW (24V ‐ PWM.) | D113: ='.'!F90 -> 594.0864
A114: ='.'!A91 -> 75 | B114: ='.'!C91 -> SIN FECHA ESTIMADA | C114: ='.'!D91 -> VOLTRONIC AXPERT VMIII 3kW (24V. Alta tensión de paneles. MPPT. Modo SUB.) | D114: ='.'!F91 -> 703.2
...

Sheet .
A2: 1 | B2: N | C2: INMEDIATO | D2: LONGI - 430w HiMOX6-LR5-54HTB (USD/watt) | E2: =Nacionalizado!D25 -> 0.23023256 | F2: =(90/430)*1.1 -> 0.23023256
A3: 2 | B3: N | C3: INMEDIATO | D3: LONGI - 645w LR7-72HVH N-Type HPBC 2.0, HI-MO X10 (USD/watt) . se vende por unidad 15% mas caro. | E3: =Nacionalizado!D26 -> 0.1914 | F3: =0.174*1.1 -> 0.1914
A4: 3 | B4: PC | C4: INMEDIATO | D4: LONGI - 610w BIFACIAL (USD/watt) - se vende por unidad 15% mas caro. | E4: =Nacionalizado!D27 -> 0.21 | F4: =0.16*1.1 -> 0.176
A5: 4 | B5: AR | C5: SIN FECHA ESTIMADA | D5: TRINA - BIFACIAL 570 (USD/watt).- se vende pallet cerrado | E5: =Nacionalizado!D28 -> 0.161 | F5: =0.14*1.15 -> 0.161
A6: 5 | B6: A | C6: SIN FECHA ESTIMADA | D6: TRINA - BIFACIAL 605w TIPO N (USD/watt)- se vende pallet cerrado | E6: =Nacionalizado!D29 -> 0.161 | F6: =0.14*1.15 -> 0.161
A7: 6 | B7: AM | C7: INMEDIATO | D7: TRINA - BIFACIAL 615w TIPO N (USD/watt)- se vende pallet cerrado | E7: =Nacionalizado!D30 -> 0.1749 | F7: =0.159*1.1 -> 0.1749
A8: 7 | B8: A | C8: INMEDIATO | D8: TRINA - MONOFACIAL 620w TIPO N (USD/watt)- se vende pallet cerrado | E8: =Nacionalizado!D31 -> 0.1749 | F8: =0.159*1.1 -> 0.1749
A9: 8 | B9: A | C9: LIQUIDACION. Quedan 9 unidades | D9: TRINA - BIFACIAL 630w TIPO N (USD/watt)- se vende pallet cerrrado (o por unidad con costo de flete al transporte de usd 35+iva por entrega total) | E9: =Nacionalizado!D32 -> 0.165 | F9: =0.15*1.1 -> 0.165 | G9: (+10RJ) -1 aristides -
A10: 9 | B10: 2 | C10: INMEDIATO | D10: TRINA - MONOFACIAL 670w (USD/watt).- se vende pallet cerrado. Se entrega en transporte en Cordoba | E10: =Nacionalizado!D33 -> 0.1815 | F10: =0.165*1.1 -> 0.1815
A11: 10 | B11: R | C11: INMEDIATO | D11: TRINA - BIFACIAL 715 (USD/watt).- se vende pallet cerrado. Se retira por depo Soldati o va a transporte en CTC | E11: =Nacionalizado!D34 -> 0.1947 | F11: =0.177*1.1 -> 0.1947
A12: 11 | B12: M | C12: INMEDIATO | D12: JINKO - M/M 475w TIGER NEO JKM475-60HL4. se vende pallet cerrado o por unidad 30% mas caro | E12: =Nacionalizado!D35 -> 0.166 | F12: =0.222*1.1 -> 0.2442
A13: 12 | B13: S | C13: LIQUIDACION. Quedan 5 unidades | D13: JINKO - BIFACIAL 585 w 72HL4-BDV (USD/watt)- Se retiran por depo soldati | E13: 0.15 | F13: =0.145*1.11 -> 0.16095 | G13: (+5RJ)
A14: 46034 | C14: INMEDIATO | D14: JINKO - MONOF 585 w 72HL4-BDV (USD/watt)- Se envia a transporte en Cordoba | E14: =Nacionalizado!D37 -> 0.18955 | F14: =0.17*1.115 -> 0.18955
A15: 13 | B15: S | C15: IMPO: 90 a 120 dias corridos | D15: JINKO - BIF 725 w TIPO N (USD/watt) se vende contenedor entero (20 pallet de 33 u) | E15: 0.16 | F15: =0.151*1.1 -> 0.1661
A16: 14 | B16: B | C16: INMEDIATO | D16: JINKO - BIFACIAL TIPO N, 620w(USD/watt)-se vende por unidad 32% mas caro. | E16: =Nacionalizado!D39 -> 0.17446 | F16: =0.1586*1.1 -> 0.17446
A17: 15 | B17: 2 | C17: INMEDIATO | D17: JINKO - M/M TOPcon, 715w(USD/watt)-se vende palet cerrado | E17: =Nacionalizado!D40 -> 0.155 | F17: =0.155 -> 0.155
A18: 16 | C18: INMEDIATO | D18: JA SOLAR - BIFACIAL 600w - se vende pallet cerrado | E18: =Nacionalizado!D41 -> 0.155 | F18: =0.155 -> 0.155
A19: 17 | B19: A | C19: INMEDIATO | D19: TRINA - BiFACIAL 620w TIPO N (USD/watt)-se vende pallet cerrado - | E19: =Nacionalizado!D42 -> 0.1749 | F19: =0.159*1.1 -> 0.1749
A20: 18 | C20: INMEDIATO. 5 a 10 dias habiles para despachar | D20: LUXEN 144C. Mono Serie 4 410Wp PERC- se vende por unidad 2.5% mas caro (35mm) -5 a 10 dias habiles para despachar | E20: =Nacionalizado!D43 -> 0.16576 | F20: =0.148*1.12 -> 0.16576
A21: 19 | C21: SIN FECHA ESTIMADA | D21: LUXEN 144C. Mono Serie 5 550Wp PERC (35mm)- se vende por unidad 2.5% mas caro - 5 a 10 dias habiles para despachar | E21: =Nacionalizado!D44 -> 0.16128 | F21: =0.144*1.12 -> 0.16128
A22: 20 | C22: SIN FECHA ESTIMADA | D22: LUXEN - 144C. M/M . Serie 5 550Wp PERC BLACK (35mm)- se vende por unidad 2.5% mas caro - 5 a 10 dias habiles para despachar | E22: =Nacionalizado!D45 -> 0.165 | F22: =0.15*1.1 -> 0.165
A23: 21 | C23: INMEDIATO. Se vende por unidad | D23: LUXEN - 132C. M/M N5 585Wp TOPcon- se vende por unidad 2.5% mas caro - 5 a 10 dias habiles para despachar | E23: =Nacionalizado!D46 -> 0.1694 | F23: =0.154*1.1 -> 0.1694
A24: 22 | C24: INMEDIATO. Se vende por unidad | D24: LUXEN - 132C. N5 RECT 585Wp TOPCon GoG bifacial - se vende por unidad 2.5% mas caro (36u x pallet) - 5 a 10 dias habiles para despachar | E24: =Nacionalizado!D47 -> 0.1694 | F24: =0.154*1.1 -> 0.1694
A25: 23 | C25: INMEDIATO. Se vende por unidad | D25: LUXEN 144C. Mono N5 RECT 630Wp TOPCon- se vende por unidad 2.5% mas caro. - 5 a 10 dias habiles para despachar | E25: =Nacionalizado!D48 -> 0.1694 | F25: =0.154*1.1 -> 0.1694
A26: 24 | C26: INMEDIATO. Se vende por unidad | D26: LUXEN - 132C. Mono N6 700Wp TOPCon GoG Bifacial- se vende por unidad 2.5% mas caro (34u x pallet) - 5 a 10 dias habiles para despachar | E26: =Nacionalizado!D49 -> 0.1694 | F26: =0.154*1.1 -> 0.1694
A27: 25 | B27: 1 | C27: LIQUIDACION PALLET CERRADO | D27: ASTROENERGY - BIFACIAL 144 CEL. N TYPE 575W CABLE 1.4M. Se vende pallet cerrado. Se entrega en transporte en Cordoba | E27: 0.15 | F27: =0.165*1.1 -> 0.1815
A28: 26 | C28: LIQUIDACION. Quedan 2 unidades | D28: ASTROENERGY - BIFACIAL 144 CEL. N TYPE 585W - se vende por unidad. Se entrega en depo soldati u oficina DOT | E28: 0.14 | G28: (+1RJ)(+1 DOT)
A29: 27 | B29: M | C29: INMEDIATO | D29: ASTROENERGY - 615w -N7_CHSM66RN(DG)F-BH dual glass - BIFACIAL. Se retira por depo Soldati | E29: =Nacionalizado!D52 -> 0.22357724 | F29: =125/615*1.1 -> 0.22357724
A30: 28 | B30: CB | C30: SIN FECHA ESTIMADA | D30: AMERISOLAR- Policristalino 340w. Pallet 36 unidades. se vende pallet cerrado | E30: =Nacionalizado!D53 -> 0.28336 | F30: =0.23*1.12*1.1 -> 0.28336
A31: 29 | B31: BC | C31: SIN FECHA ESTIMADA | D31: AMERISOLAR - MONOCRISTALINO AS-7M108N-HC-440W. se vende por unidad 32% mas caro. 36u x pallet -Entrega gratis en GBA. | E31: =Nacionalizado!D54 -> 0.187 | F31: =0.17*1.1 -> 0.187
A32: 30 | B32: BCV | C32: SIN FECHA ESTIMADA | D32: AMERISOLAR - MONOCRISTALINO AS-7M144-HC-555W. se vende por unidad 32% mas caro. -Entrega gratis en GBA. | E32: =Nacionalizado!D55 -> 0.1668106 | F32: =0.121*1.22*1.13 -> 0.1668106
A33: 31 | B33: BC | C33: INMEDIATO. Se vende por unidad | D33: AMERISOLAR - MONOCRISTALINO AS-7M144-HC-580W. precio pallet cerrado. Entrega gratis en GBA. Por unidad 30% mas caro | E33: =Nacionalizado!D56 -> 0.15859218 | F33: =(88.83/580)*0.95*1.09 -> 0.15859218
A34: 32 | B34: CB | C34: SIN FECHA ESTIMADA | D34: AMERISOLAR - MONOCRISTALINO AS-8M120-HC-600W. se vende por unidad 30% mas caro. | E34: =Nacionalizado!D57 -> 0.14 | F34: =0.125*1.12 -> 0.14
A35: 33 | C35: INMEDIATO. Quedan 28 unidades se venden juntas | D35: SUNPRO - Monoc, TOPCON, SPDG585-N144M10-585W con Marco Negro. BIFACIAL. se venden las 28 unidades juntas | E35: =Nacionalizado!D58 -> 0.1595 | F35: =0.145*1.1 -> 0.1595
A36: 34 | C36: INMEDIATO | D36: HAITAI - Monocristalino, media celda, Anti LID HTM585DMH5-72NT-585W. Pallet 36 unidades. se vende por unidad 32% mas caro. | E36: =Nacionalizado!D59 -> 0.17504197 | F36: =(97.99/585)*0.95*1.1 -> 0.17504197
A37: 35 | C37: INGRESA ABRIL | D37: HAITAI - Monocristalino, media celda, HTM415MH5-54 415W. Pallet 36 unidades. se vende por unidad 32% mas caro. | E37: =Nacionalizado!D60 -> 0.1495 | F37: =0.115*1.3 -> 0.1495
A38: 36 | C38: INMEDIATO | D38: HAITAI, Monocristalino, media celda, Anti LID, Bifacial, HTM630DMH6-66NT BIFACIAL 630W. Pallet 36 unidades.se vende por unidad 32% mas caro | E38: =Nacionalizado!D61 -> 0.1826 | F38: =0.166*1.1 -> 0.1826
A39: 37 | C39: INMEDIATO | D39: TLC - Anti LID TCL-MI585 DH182-72NT 585W BIFACIAL. Pallet 36 unidades. se vende por unidad 32% mas caro | E39: =Nacionalizado!D62 -> 0.16264487 | F39: =(91.05/585)*0.95*1.1 -> 0.16264487
A40: 38 | C40: INMEDIATO | D40: NUUKO - monof 550w (pallet 31 u) - se vende minimo 10 u | E40: =Nacionalizado!D63 -> 0.161
A41: 39 | C41: INMEDIATO | D41: NUUKO - bif 615w topcon (pallet 36 u) - se vende minimo 10 u | E41: =Nacionalizado!D64 -> 0.169
A42: INVERSORES ON GRID SUNGROW
A43: 39-1 | C43: INMEDIATO | D43: Inversor On-Grid SunGrow Trifasico 15 KW | E43: =Nacionalizado!D66 -> 1297.8336 | F43: =1158.78*1.12 -> 1297.8336
A44: 39-2 | C44: INMEDIATO | D44: Inversor On-Grid SunGrow Trifasico 20 KW | E44: =Nacionalizado!D67 -> 1433.993 | F44: =1303.63*1.1 -> 1433.993
A45: 39-3 | C45: INMEDIATO | D45: Inversor On-Grid SunGrow Trifasico 25 KW | E45: =Nacionalizado!D68 -> 1779.206 | F45: =1617.46*1.1 -> 1779.206
A46: 39-4 | C46: INMEDIATO | D46: Inversor On-Grid SunGrow Trifasico 30 KW | E46: =Nacionalizado!D69 -> 2044.768 | F46: =1858.88*1.1 -> 2044.768
A47: 39-5 | C47: INMEDIATO | D47: Inversor On-Grid SunGrow Trifasico 40 KW | E47: =Nacionalizado!D70 -> 2400.607 | F47: =2182.37*1.1 -> 2400.607
A48: 39-6 | C48: INMEDIATO | D48: Inversor On-Grid SunGrow Trifasico 50 KW | E48: =Nacionalizado!D71 -> 2798.4544 | F48: =2498.62*1.12 -> 2798.4544
A49: 39-7 | C49: INMEDIATO | D49: Inversor On-Grid SunGrow Trifasico 75 KW | E49: =Nacionalizado!D72 -> 3823.975 | F49: =3059.18*1.25 -> 3823.975
A50: 39-8 | C50: INMEDIATO | D50: Inversor On-Grid SunGrow Trifasico 110 KW | E50: =Nacionalizado!D73 -> 5066.765 | F50: =4606.15*1.1 -> 5066.765
A51: 39-9 | C51: INMEDIATO | D51: Inversor On-Grid SunGrow Trifasico 250 KW | E51: =Nacionalizado!D74 -> 9942.328 | F51: =9038.48*1.1 -> 9942.328
A52: 39-10 | C52: INMEDIATO | D52: Inversor On-Grid SunGrow Trifasico 333 KW | E52: =Nacionalizado!D75 -> 12236.719 | F52: =11124.29*1.1 -> 12236.719
A53: INVERSORES ON GRID SUNGROW
A54: 40 | B54: L | C54: SIN FECHA ESTIMADA | D54: Inversor de inyección a red GOODWE 1500W Monof. (GW1500 - XS-30) | E54: =Nacionalizado!D77 -> 186.3 | F54: =162*1.15 -> 186.3
A55: 41 | B55: L | C55: INMEDIATO | D55: IMicronversor de inyección a red GOODWE 2000w Monof. (GW2000-MIS) | E55: =Nacionalizado!D78 -> 279.0625 | F55: =223.25*1.25 -> 279.0625
A56: 42 | B56: L | C56: INMEDIATO | D56: Inversor de inyección a red GOODWE 3600W Monof. c/AFCI (GW3.6K-DNS-G40) | E56: =Nacionalizado!D79 -> 401.375 | F56: =321.1*1.25 -> 401.375
A57: 43 | B57: CL | C57: INMEDIATO. 5 a 10 dias habiles para despachar | D57: Inversor de inyección a red GOODWE 6000W Trif. c/AFCI | E57: =Nacionalizado!D80 -> 610.88 | F57: =640*0.83*1.15 -> 610.88
A58: 44 | B58: / VLC | C58: INMEDIATO. 5 a 10 dias habiles para despachar | D58: Inversor de inyección a red GOODWE 10kW Trif. (10K-SDT30) | E58: =Nacionalizado!D81 -> 779.52 | F58: =696*1.12 -> 779.52
A59: 45 | B59: L | C59: SIN FECHA ESTIMADA | D59: Inversor de inyección a red GOODWE 12kW Trif. c/Wifi | E59: =Nacionalizado!D82 -> 2168.2742 | F59: =(2898600/1.21*0.85)/1033*1.1 -> 2168.2742
A60: 46 | B60: / LC | C60: INMEDIATO. 5 a 10 dias habiles para despachar | D60: Inversor de inyección a red GOODWE 15kW Trif. (15K-SDT-30) | E60: =Nacionalizado!D83 -> 860.16 | F60: =768*1.12 -> 860.16
A61: 47 | B61: / VLC | C61: INMEDIATO. 5 a 10 dias habiles para despachar | D61: Inversor de inyección a red GOODWE 20kW Trif.(20K-SDT-30) | E61: =Nacionalizado!D84 -> 987.84 | F61: =882*1.12 -> 987.84
A62: 48 | B62: / ML | C62: INMEDIATO. 5 a 10 dias habiles para despachar | D62: Inversor de inyección a red GOODWE 25kW Trif. c/AFCI (25K-SDT-C30-AFCI) | E62: =Nacionalizado!D85 -> 1113.28 | F62: =994*1.12 -> 1113.28
A63: 49 | B63: C/ ML | C63: INMEDIATO. 5 a 10 dias habiles para despachar | D63: Inversor de inyección a red GOODWE 30kW Trif. c/AFCI (30K-SDT-C30-AFCI) | E63: =Nacionalizado!D86 -> 1227.52 | F63: =1096*1.12 -> 1227.52
A64: 50 | B64: / ML | C64: INMEDIATO. 5 a 10 dias habiles para despachar | D64: Inversor de inyección a red GOODWE 33kW Trif. c/AFCI (30K-SDT-C30-AFCI) | E64: =Nacionalizado!D87 -> 1232 | F64: =1120*1.1 -> 1232
A65: 51 | B65: / MVL | C65: INMEDIATO. 5 a 10 dias habiles para despachar | D65: Inversor de inyección a red GOODWE 36kW Trif. c/AFCI (30K-SDT-C30-AFCI) | E65: =Nacionalizado!D88 -> 1276 | F65: =1160*1.1 -> 1276
A66: 52 | B66: / L | C66: INMEDIATO. 5 a 10 dias habiles para despachar | D66: Inversor de inyección a red GOODWE 40kW Trif. c/AFCI (40K-SDT-C30-AFCI) | E66: =Nacionalizado!D89 -> 1460.8 | F66: =1328*1.1 -> 1460.8
A67: 53 | B67: L | C67: INMEDIATO. 5 a 10 dias habiles para despachar | D67: Inversor de inyección a red GOODWE 30kW Trif. MT (30K-MT) | E67: =Nacionalizado!D90 -> 1842.6 | F67: =1660*1.11 -> 1842.6
A68: 54 | B68: / | C68: SIN FECHA ESTIMADA | D68: Inversor de inyección a red GOODWE 50kW Trif. AFCI | E68: =Nacionalizado!D91 -> 1634.6 | F68: =1486*1.1 -> 1634.6
A69: 55 | B69: / L | C69: INMEDIATO. 5 a 10 dias habiles para despachar | D69: Inversor de inyección a red GOODWE 60kW Trif. AFCI (GW 60KS-MT-AFCI) | E69: =Nacionalizado!D92 -> 2421.9 | F69: =2106*1.15 -> 2421.9
A70: 56 | B70: / VL | C70: INMEDIATO. 5 a 10 dias habiles para despachar | D70: Inversor de inyección a red GOODWE 80kW Trif. c/ AFCI (GW80K-SMT-AFCI) | E70: =Nacionalizado!D93 -> 2442 | F70: =2220*1.1 -> 2442
A71: 57 | B71: L | C71: INMEDIATO. 5 a 10 dias habiles para despachar | D71: Inversor de inyección a red GOODWE 100kW Trif. (GW100K GT). Se entrega en transporte en Rosario | E71: =Nacionalizado!D94 -> 3847.8 | F71: =3498*1.1 -> 3847.8
A72: 58 | B72: / L | C72: INMEDIATO. 5 a 10 dias habiles para despachar | D72: Inversor de inyección a red GOODWE 110kW Trif. C/AFCI | E72: =Nacionalizado!D95 -> 3907.2 | F72: =3520*1.11 -> 3907.2
A73: 59 | B73: / VL | C73: INMEDIATO. 5 a 10 dias habiles para despachar | D73: Inversor de inyección a red GOODWE 100KW Trifasico AFCI | E73: =Nacionalizado!D96 -> 4040.96 | F73: =3608*1.12 -> 4040.96
A74: 60 | B74: C | C74: INMEDIATO. 5 a 10 dias habiles para despachar | D74: Inversor de inyección a red GOODWE 50kW GW50K-SDT-C30 | E74: =Nacionalizado!D97 -> 2365
A75: 61 | B75: L | C75: INMEDIATO. 5 a 10 dias habiles para despachar | D75: Inversor de inyección a red GOODWE 125KW Trifasico. (GW100K GT). Se entrega en transporte en Rosario | E75: =Nacionalizado!D98 -> 4374.72 | F75: =3906*1.12 -> 4374.72
A76: 62 | B76: L | C76: INMEDIATO. 5 a 10 dias habiles para despachar | D76: Smart meter GMK110 monofasico | E76: =Nacionalizado!D99 -> 195.125 | F76: =175*1.115 -> 195.125
A77: 63 | B77: L | C77: INMEDIATO. 5 a 10 dias habiles para despachar | D77: Smart meter GMK330 trifasico | E77: =Nacionalizado!D100 -> 379.5 | F77: =330*1.15 -> 379.5
A78: INVERSORES ON GRID HUAWEI
A79: 64 | B79: 1R | C79: INMEDIATO | D79: INVERSOR TRIFASICO HUAWEI SUN2000-40KTL-M3 | E79: =Nacionalizado!D102 -> 2711.83 | F79: =2465.3*1.1 -> 2711.83
A80: 65 | B80: 1 | C80: INMEDIATO | D80: INVERSOR TRIFASICO HUAWEI SUN2000-50KTL-M3 | E80: =Nacionalizado!D103 -> 2937.979 | F80: =2670.89*1.1 -> 2937.979
A81: 66 | B81: 1R | C81: INMEDIATO | D81: INVERSOR TRIFASICO HUAWEI SUN2000-100KTL M2- | E81: =Nacionalizado!D104 -> 5645.893 | F81: =5132.63*1.1 -> 5645.893
A82: 67 | B82: 1R | C82: INMEDIATO | D82: INVERSOR TRIFASICO HUAWEI SUN2000-150K-MG0 - | E82: =Nacionalizado!D105 -> 6325 | F82: =5500*1.15 -> 6325
A83: 68 | B83: 1 | C83: INMEDIATO | D83: INVERSOR TRIFASICO 6MPPT 800V 330KW HUAWEI | E83: =Nacionalizado!D106 -> 9898.9 | F83: =8999*1.1 -> 9898.9
A84: 69 | B84: 1R | C84: INMEDIATO | D84: Huawei SmartPS-250A-T0 - Smart Power Sensor | E84: =Nacionalizado!D107 -> 173.7 | F84: =193*0.75*1.2 -> 173.7
A85: 70 | B85: 1R | C85: INMEDIATO | D85: Huawei SDongleA-05 | E85: =Nacionalizado!D108 -> 62.1 | F85: =69*0.75*1.2 -> 62.1
A86: 71 | B86: 1 | C86: INMEDIATO | D86: DongleB-06-AU - Dongle 4G | E86: =Nacionalizado!D109 -> 152.1 | F86: =169*0.75*1.2 -> 152.1
A87: INVERSORES VOLTRONIC
A88: 72 | B88: F | C88: SIN FECHA ESTIMADA | D88: INVERSOR OFF GRID - AXPERT VM 2KW | E88: =Nacionalizado!D111 -> 520.24 | F88: =464.5*1.12 -> 520.24
A89: 73 | B89: F | C89: SIN FECHA ESTIMADA | D89: VOLTRONIC AXPERT VM 1kW | E89: =Nacionalizado!D112 -> 322 | F89: 322
A90: 74 | B90: J | C90: SIN FECHA ESTIMADA | D90: VOLTRONIC AXPERT VP 3kW (24V ‐ PWM.) | E90: =Nacionalizado!D113 -> 594.0864 | F90: 594.0864
A91: 75 | B91: J | C91: SIN FECHA ESTIMADA | D91: VOLTRONIC AXPERT VMIII 3kW (24V. Alta tensión de paneles. MPPT. Modo SUB.) | E91: =Nacionalizado!D114 -> 703.2 | F91: =586*1.2 -> 703.2
A92: 76 | B92: J | C92: SIN FECHA ESTIMADA | D92: VOLTRONIC AXPERT VMIV 5,6kW (48V. Alta tensión de paneles. MPPT. Modo SUB.) | E92: =Nacionalizado!D115 -> 957.6 | F92: =798*1.2 -> 957.6
A93: 77 | B93: J | C93: INMEDIATO | D93: VOLTRONIC AXPERT MAX 7,2kW (48V. Alta tensión de paneles. 2xMPPT. Modo SUB.) | E93: =Nacionalizado!D116 -> 900 | F93: =998*1.2 -> 1197.6
A94: 78 | B94: J | C94: INMEDIATO | D94: Módulo WiFi para Axpert VMIII | E94: =Nacionalizado!D117 -> 90 | F94: =60*1.2 -> 72
A95: INVERSORES ON GRID DEYE - ATENCION METER!
A96: 79 | B96: G | C96: INMEDIATO | D96: Microinversor 1000W 2MPPT Mono c/Wifi DEYE (SUN-M100G4-EU-Q0) | E96: =Nacionalizado!D119 -> 269.5 | F96: =275*0.98 -> 269.5
A97: 79-1 | C97: INGRESA MAYO | D97: Microinversor 2250W 4MPPT Mono c/Wifi c/ Zero Export DEYE (SUN-M225G4-EU-Q0-I) | E97: =Nacionalizado!D120 -> 365 | F97: =365 -> 365
A98: 80 | B98: 1G | C98: INMEDIATO | D98: On Grid 3KVA 1MPPT Mono c/CT y Wifi DEYE (SUN-3K-G04LP1-EU-AM1) | E98: =Nacionalizado!D121 -> 365 | F98: 365
A99: 80-1 | B99: 1 | C99: INMEDIATO | D99: On Grid 5kW 2MPPT Mono c/CT y WiFi DEYE (SUN-5K-G05LP1-EU-AM2) | E99: =Nacionalizado!D122 -> 525 | F99: =525 -> 525
A100: 81 | B100: 1GEJ | C100: INMEDIATO | D100: On Grid 6KVA 2MPPT Mono con meter c/ WiFi DEYE (SUN-6K-G05LP1-EU-AM2) | E100: =Nacionalizado!D123 -> 805 | F100: =700*1.15 -> 805
A101: 82 | B101: GEJ | C101: INMEDIATO | D101: On Grid 6kW 2MPPT Trif c/WiFi s/Meter DEYE(SUN-6K-G06P3-EU-AM2-P1) | E101: =Nacionalizado!D124 -> 568.4 | F101: =580*0.98 -> 568.4
...
